points_in_rbbox/__init__.py
points_in_rbbox/utils.py
points_in_rbbox-0.0.0.dist-info/LICENSE
points_in_rbbox-0.0.0.dist-info/METADATA
points_in_rbbox-0.0.0.dist-info/WHEEL
points_in_rbbox-0.0.0.dist-info/top_level.txt
points_in_rbbox-0.0.0.dist-info/RECORD
