Metadata-Version: 2.1
Name: points_in_rbbox
Version: 0.0.0
Summary: point-in-rbbox CUDA ops
Home-page: https://github.com/lh9171338/points-in-rbbox
Author: lh9171338
Author-email: lihao2015@whu.edu.cn
Project-URL: Bug Tracker, https://github.com/lh9171338/points-in-rbbox/issues
Classifier: Programming Language :: Python :: 3
Classifier: License :: OSI Approved :: MIT License
Classifier: Operating System :: OS Independent
Requires-Python: >=3.6
License-File: LICENSE
Requires-Dist: torch
Provides-Extra: all
Requires-Dist: test ; extra == 'all'
Provides-Extra: test
Requires-Dist: lh-tool >=1.12.1 ; extra == 'test'
